Metadata-Version: 2.1
Name: polybius-square-pro
Version: 1.0.0
Summary: An improved encryption and decryption tool from the Polybius Square.
Home-page: https://github.com/wzyskq/polybius_square_pro
Author: Foces Becken
Author-email: 
License: MIT
Keywords: python,polybius,cipher,encode
Platform: UNKNOWN
Classifier: Development Status :: 4 - Beta
Classifier: License :: OSI Approved :: MIT License
Classifier: Programming Language :: Python :: 3
Classifier: Topic :: Security :: Cryptography
License-File: LICENSE
